drf_easily_saas/__init__.py
drf_easily_saas/admin.py
drf_easily_saas/app.py
drf_easily_saas/auth/__init__.py
drf_easily_saas/auth/firebase/__init__.py
drf_easily_saas/auth/firebase/protect.py
drf_easily_saas/exceptions/__init__.py
drf_easily_saas/exceptions/base.py
drf_easily_saas/exceptions/config.py
drf_easily_saas/exceptions/firebase.py
drf_easily_saas/exceptions/stripe.py
drf_easily_saas/management/__init__.py
drf_easily_saas/management/commands/__init__.py
drf_easily_saas/management/commands/syncfirebaseusers.py
drf_easily_saas/migrations/0001_initial.py
drf_easily_saas/migrations/0002_alter_subscription_options_and_more.py
drf_easily_saas/migrations/0003_alter_subscription_unique_together.py
drf_easily_saas/migrations/__init__.py
drf_easily_saas/models.py
drf_easily_saas/payment/__init__.py
drf_easily_saas/payment/manager.py
drf_easily_saas/payment/serializers.py
drf_easily_saas/payment/stripe/__init__.py
drf_easily_saas/payment/stripe/serializers.py
drf_easily_saas/payment/stripe/urls.py
drf_easily_saas/payment/stripe/views.py
drf_easily_saas/payment/urls.py
drf_easily_saas/schemas/__init__.py
drf_easily_saas/schemas/claims.py
drf_easily_saas/schemas/config.py
drf_easily_saas/schemas/constants.py
drf_easily_saas/schemas/firebase.py
drf_easily_saas/schemas/stripe.py
drf_easily_saas/schemas/utils.py
drf_easily_saas/settings.py
drf_easily_saas/tests/__init__.py
drf_easily_saas/tests/user_stories/__init__.py
drf_easily_saas/tests/user_stories/test_checkout.py
drf_easily_saas/urls.py
drf_easily_saas/utils/__init__.py
drf_easily_saas/utils/db.py
drf_easily_saas/utils/urls.py
drf_easily_saas-0.0.4.dist-info/METADATA
drf_easily_saas-0.0.4.dist-info/WHEEL
drf_easily_saas-0.0.4.dist-info/RECORD
