Metadata-Version: 2.1
Name: drf_easily_saas
Version: 0.0.4
Summary: This package is complete tools for sass building
Home-page: https://github.com/alexandre-meline/drf_easily_sass/
Keywords: Django,Firebase,Authentication,User Synchronization,DRF,Python,User Management,Security,API,JSON Web Tokens,Payment,Stripe
Author: Alexandre Meline
Author-email: alexandre.meline.dev@gmail.com
Requires-Python: >=3.10,<4.0
Classifier: Programming Language :: Python :: 3
Classifier: Programming Language :: Python :: 3.10
Classifier: Programming Language :: Python :: 3.11
Classifier: Programming Language :: Python :: 3.12
Requires-Dist: django (>=5.0.4,<6.0.0)
Requires-Dist: djangorestframework (>=3.15.1,<4.0.0)
Requires-Dist: drf-spectacular (>=0.27.2,<0.28.0)
Requires-Dist: firebase-admin (>=6.5.0,<7.0.0)
Requires-Dist: google-cloud-functions (>=1.16.3,<2.0.0)
Requires-Dist: mkdocs (>=1.6.0,<2.0.0)
Requires-Dist: mkdocs-material (>=9.5.19,<10.0.0)
Requires-Dist: pydantic (>=2.7.1,<3.0.0)
Requires-Dist: python-dotenv (>=1.0.1,<2.0.0)
Requires-Dist: stripe (>=9.3.0,<10.0.0)
